README
_sane.c
sane.py
setup.py
pysane.egg-info/PKG-INFO
pysane.egg-info/SOURCES.txt
pysane.egg-info/dependency_links.txt
pysane.egg-info/top_level.txt