Metadata-Version: 1.0
Name: pysane
Version: 2.0.1
Summary: This is the pysane package
Home-page: UNKNOWN
Author: UNKNOWN
Author-email: UNKNOWN
License: UNKNOWN
Platform: UNKNOWN
